ripe.atlas.sagan-1.3.1-py3.6-nspkg.pth
ripe/atlas/sagan/__init__.py
ripe/atlas/sagan/base.py
ripe/atlas/sagan/dns.py
ripe/atlas/sagan/http.py
ripe/atlas/sagan/ntp.py
ripe/atlas/sagan/ping.py
ripe/atlas/sagan/ssl.py
ripe/atlas/sagan/traceroute.py
ripe/atlas/sagan/version.py
ripe/atlas/sagan/wifi.py
ripe/atlas/sagan/helpers/__init__.py
ripe/atlas/sagan/helpers/abuf.py
ripe/atlas/sagan/helpers/compatibility.py
ripe.atlas.sagan-1.3.1.dist-info/LICENSE
ripe.atlas.sagan-1.3.1.dist-info/METADATA
ripe.atlas.sagan-1.3.1.dist-info/WHEEL
ripe.atlas.sagan-1.3.1.dist-info/namespace_packages.txt
ripe.atlas.sagan-1.3.1.dist-info/top_level.txt
ripe.atlas.sagan-1.3.1.dist-info/RECORD
