Metadata-Version: 2.1
Name: ripe.atlas.sagan
Version: 1.3.1
Summary: A parser for RIPE Atlas measurement results
Home-page: https://github.com/RIPE-NCC/ripe.atlas.sagan
Author: The RIPE Atlas Team
Author-email: atlas@ripe.net
Maintainer: The RIPE Atlas Team
Maintainer-email: atlas@ripe.net
License: GPLv3
Download-URL: https://github.com/RIPE-NCC/ripe.atlas.sagan
Platform: UNKNOWN
Classifier: Operating System :: POSIX
Classifier: Operating System :: Unix
Classifier: Programming Language :: Python
Classifier: Programming Language :: Python :: 2.7
Classifier: Programming Language :: Python :: 3.5
Classifier: Programming Language :: Python :: 3.6
Classifier: Programming Language :: Python :: 3.7
Classifier: Topic :: Internet :: WWW/HTTP
Requires-Dist: python-dateutil
Requires-Dist: pytz
Requires-Dist: cryptography
Provides-Extra: doc
Requires-Dist: sphinx ; extra == 'doc'
Provides-Extra: fast
Requires-Dist: ujson ; extra == 'fast'
